qualysdk/__init__.py
qualysdk/admin/__init__.py
qualysdk/admin/data_classes/User.py
qualysdk/admin/data_classes/__init__.py
qualysdk/admin/rbac.py
qualysdk/auth/__init__.py
qualysdk/auth/base.py
qualysdk/auth/basic.py
qualysdk/auth/platform_picker.py
qualysdk/auth/token.py
qualysdk/base/__init__.py
qualysdk/base/base_class.py
qualysdk/base/base_list.py
qualysdk/base/call_api.py
qualysdk/base/call_schema.py
qualysdk/base/call_schemas/__init__.py
qualysdk/base/call_schemas/admin_schema.py
qualysdk/base/call_schemas/certview_schema.py
qualysdk/base/call_schemas/cloudagent_schema.py
qualysdk/base/call_schemas/cs_schema.py
qualysdk/base/call_schemas/gav_schema.py
qualysdk/base/call_schemas/pm_schema.py
qualysdk/base/call_schemas/tagging_schema.py
qualysdk/base/call_schemas/totalcloud_schema.py
qualysdk/base/call_schemas/vmdr_schema.py
qualysdk/base/call_schemas/was_schema.py
qualysdk/base/convert_bools_and_nones.py
qualysdk/base/csv_export.py
qualysdk/base/json_export.py
qualysdk/base/post_init_parser.py
qualysdk/base/printutils.py
qualysdk/base/serializable_mixin.py
qualysdk/base/xml_parser.py
qualysdk/cert/__init__.py
qualysdk/cert/data_classes/Asset.py
qualysdk/cert/data_classes/Certificate.py
qualysdk/cert/data_classes/__init__.py
qualysdk/cert/list_certs.py
qualysdk/cli/cli_updater.py
qualysdk/cli/qualysdk_cert.py
qualysdk/cli/qualysdk_gav.py
qualysdk/cli/qualysdk_pm.py
qualysdk/cli/qualysdk_rbac.py
qualysdk/cli/qualysdk_tag.py
qualysdk/cli/qualysdk_users.py
qualysdk/cli/qualysdk_was.py
qualysdk/cloud_agent/__init__.py
qualysdk/cloud_agent/calls.py
qualysdk/cloud_agent/data_classes/Agent.py
qualysdk/cloud_agent/data_classes/CloudAgentTag.py
qualysdk/cloud_agent/data_classes/__init__.py
qualysdk/cloud_agent/prepare_criteria.py
qualysdk/cloud_agent/purge.py
qualysdk/cs/__init__.py
qualysdk/cs/container/__init__.py
qualysdk/cs/container/container_calls.py
qualysdk/cs/data_classes/__init__.py
qualysdk/cs/data_classes/container.py
qualysdk/cs/data_classes/software.py
qualysdk-0.3.18.dist-info/METADATA
qualysdk-0.3.18.dist-info/WHEEL
qualysdk-0.3.18.dist-info/entry_points.txt
qualysdk-0.3.18.dist-info/licenses/LICENSE
qualysdk-0.3.18.dist-info/RECORD
