Metadata-Version: 2.4
Name: qualysdk
Version: 0.3.18
Summary: SDK for interacting with Qualys APIs, across most modules the platform offers.
License: MIT
License-File: LICENSE
Author: 0x41424142
Author-email: jake@jakelindsay.uk
Maintainer: Jake Lindsay
Maintainer-email: jake@jakelindsay.uk
Requires-Python: >=3.12,<4.0
Classifier: Development Status :: 4 - Beta
Classifier: Intended Audience :: Developers
Classifier: Intended Audience :: Information Technology
Classifier: License :: OSI Approved :: MIT License
Classifier: Programming Language :: Python :: 3
Classifier: Programming Language :: Python :: 3.12
Classifier: Programming Language :: Python :: 3.13
Classifier: Programming Language :: Python :: 3.14
Classifier: Topic :: Security
Requires-Dist: bs4 (>=0.0.2,<0.0.3)
Requires-Dist: defusedxml (>=0.7.1,<0.8.0)
Requires-Dist: frozendict (>=2.4.7,<3.0.0)
Requires-Dist: lxml (>=6.0.2,<7.0.0)
Requires-Dist: mkdocs-material (>=9.7.1,<10.0.0)
Requires-Dist: numpy (>=2.4.1,<3.0.0)
Requires-Dist: packaging (==25.0)
Requires-Dist: pandas (>=2.3.3,<3.0.0)
Requires-Dist: psycopg2 (>=2.9.11,<3.0.0) ; sys_platform == "win32"
Requires-Dist: psycopg2-binary (>=2.9.11,<3.0.0) ; sys_platform == "darwin"
Requires-Dist: psycopg2-binary (>=2.9.11,<3.0.0) ; sys_platform == "linux"
Requires-Dist: pymdown-extensions (>=10.20,<11.0)
Requires-Dist: pymssql (>=2.1.5,<3.0.0)
Requires-Dist: pymysql (>=1.1.2,<2.0.0)
Requires-Dist: requests (>=2.32.5,<3.0.0)
Requires-Dist: sqlalchemy (>=2.0.45,<3.0.0)
Requires-Dist: xlsxwriter (>=3.2.9,<4.0.0)
Requires-Dist: xmltodict (>=1.0.2,<2.0.0)
Project-URL: Documentation, https://qualysdk.jakelindsay.uk
Project-URL: Homepage, https://github.com/0x41424142/qualysdk
Project-URL: Issues, https://github.com/0x41424142/qualysdk/issues
Project-URL: Repository, https://github.com/0x41424142/qualysdk
